Metadata-Version: 2.3
Name: sema4ai-common
Version: 0.2.1
Summary: Sema4AI Common
License: Apache-2.0
Author: Sema4.ai Engineering
Author-email: engineering@sema4.ai
Requires-Python: >=3.11,<4.0
Classifier: License :: OSI Approved :: Apache Software License
Classifier: Programming Language :: Python :: 3
Classifier: Programming Language :: Python :: 3.11
Classifier: Programming Language :: Python :: 3.12
Classifier: Programming Language :: Python :: 3.13
Requires-Dist: msgspec (>=0.18)
Requires-Dist: psutil (>=5.0,<7.0)
Requires-Dist: pyyaml (>=6.0,<7.0)
Requires-Dist: sema4ai-http-helper (>=2.0.0,<3.0.0)
Project-URL: Repository, https://github.com/Sema4AI/actions/
